{
  "providers": [
    {
      "type": "bitmap",
      "file": "glyphs/powergolf_logo.png",
      "height": 16,
      "ascent": 16,
      "chars": [
        "耀"
      ]
    },
    {
      "type": "bitmap",
      "file": "glyphs/ranks/team.png",
      "height": 8,
      "ascent": 7,
      "chars": [
        "⾣"
      ]
    },
    {
      "type": "bitmap",
      "file": "glyphs/ranks/moderator.png",
      "height": 8,
      "ascent": 7,
      "chars": [
        "⫽"
      ]
    },
    {
      "type": "bitmap",
      "file": "glyphs/ranks/star.png",
      "height": 8,
      "ascent": 7,
      "chars": [
        "⟎"
      ]
    },
    {
      "type": "bitmap",
      "file": "glyphs/ranks/elite.png",
      "height": 8,
      "ascent": 7,
      "chars": [
        "⎖"
      ]
    },
    {
      "type": "bitmap",
      "file": "glyphs/ranks/mvp.png",
      "height": 8,
      "ascent": 7,
      "chars": [
        "⑄"
      ]
    },
    {
      "type": "bitmap",
      "file": "glyphs/ranks/vip_plus.png",
      "height": 8,
      "ascent": 7,
      "chars": [
        "ⱊ"
      ]
    },
    {
      "type": "bitmap",
      "file": "glyphs/ranks/vip.png",
      "height": 8,
      "ascent": 7,
      "chars": [
        "Ⳡ"
      ]
    },
    {
      "type": "bitmap",
      "file": "glyphs/ranks/guest.png",
      "height": 8,
      "ascent": 7,
      "chars": [
        "⎭"
      ]
    },
    {
      "type": "bitmap",
      "file": "glyphs/gui/main_menu.png",
      "height": 257,
      "ascent": 14,
      "chars": [
        "圝"
      ]
    },
    {
      "type": "bitmap",
      "file": "glyphs/gui/manage_party_menu.png",
      "height": 257,
      "ascent": 14,
      "chars": [
        "⮉"
      ]
    },
    {
      "type": "bitmap",
      "file": "glyphs/icon16.png",
      "height": 13,
      "ascent": 9,
      "chars": [
        "䶵"
      ]
    },
    {
      "type": "bitmap",
      "file": "glyphs/blank.png",
      "height": -3,
      "ascent": -2000,
      "chars": [
        "⡝"
      ]
    },
    {
      "type": "bitmap",
      "file": "glyphs/balloons.png",
      "height": 8,
      "ascent": 7,
      "chars": [
        "⽯"
      ]
    },
    {
      "type": "bitmap",
      "file": "glyphs/blank.png",
      "height": 8,
      "ascent": 7,
      "chars": [
        "𐅆"
      ]
    }
  ]
}